idabulksms/__init__.py
idabulksms/auth.py
idabulksms/functions.py
idabulksms-0.0.1.dist-info/LICENSE
idabulksms-0.0.1.dist-info/METADATA
idabulksms-0.0.1.dist-info/WHEEL
idabulksms-0.0.1.dist-info/top_level.txt
idabulksms-0.0.1.dist-info/RECORD
