Metadata-Version: 2.1
Name: idabulksms
Version: 0.0.1
Summary: A package that allow you to send  bulk sms in all countries. 
Home-page: https://github.com/tuganimana/idasms
Author: Telesphore Tuganimana
Author-email: telesphore@idatech.rw
License: UNKNOWN
Platform: UNKNOWN
Classifier: Programming Language :: Python :: 3
Classifier: License :: OSI Approved :: MIT License
Classifier: Operating System :: OS Independent
Requires-Python: >=3.6
